bangladatetime/__init__.py
bangladatetime/date.py
bangladatetime-0.0.2.dist-info/LICENSE
bangladatetime-0.0.2.dist-info/METADATA
bangladatetime-0.0.2.dist-info/WHEEL
bangladatetime-0.0.2.dist-info/top_level.txt
bangladatetime-0.0.2.dist-info/RECORD
